setup.py
applepay/__init__.py
applepay/payment.py
applepay.egg-info/PKG-INFO
applepay.egg-info/SOURCES.txt
applepay.egg-info/dependency_links.txt
applepay.egg-info/requires.txt
applepay.egg-info/top_level.txt
tests/__init__.py
tests/applepay_test.py