Metadata-Version: 1.1
Name: applepay
Version: 0.3.0
Summary: a Python library for decrypting Apple Pay payment tokens.
Home-page: https://github.com/halturin/applepay
Author: Taras Halturin
Author-email: halturin@gmail.com
License: BSD
Keywords: applepay payment tokens
Platform: UNKNOWN
Classifier: Development Status :: 4 - Beta
Classifier: Topic :: Utilities
Classifier: License :: OSI Approved :: BSD License
